setup.cfg
setup.py
boxup_core/__init__.py
boxup_core/boxup_core.py
boxup_core.egg-info/PKG-INFO
boxup_core.egg-info/SOURCES.txt
boxup_core.egg-info/dependency_links.txt
boxup_core.egg-info/requires.txt
boxup_core.egg-info/top_level.txt
boxup_types/__init__.py
boxup_types/boxup_types.py