Metadata-Version: 1.1
Name: boxup-core
Version: 0.0.2
Summary: The main boxup programm for showing different datasources at different visualizations
Home-page: https://github.com/xamgreen/boxup_core
Author: Maximilian, Noppel
Author-email: noppelmax@googlemail.com
License: GPLv2, see LICENSE.txt
Download-URL: https://github.com/xamgreen/boxup_core/tarball/0.0.2
Keywords: weatherradar,openweathermap,raspberrypi,gpio,diy
Platform: UNKNOWN
